uadatasdk/__init__.py
uadatasdk/api.py
uadatasdk/client.py
uadatasdk/server_clien.py
uadatasdk/utlis.py
uadatasdk-0.0.6.dist-info/LICENSE
uadatasdk-0.0.6.dist-info/METADATA
uadatasdk-0.0.6.dist-info/WHEEL
uadatasdk-0.0.6.dist-info/top_level.txt
uadatasdk-0.0.6.dist-info/RECORD
