Metadata-Version: 2.1
Name: uadatasdk
Version: 0.0.6
Summary: Widening data acquisition program
Home-page: UNKNOWN
Author: 
Author-email: 
License: Apache License v2
Platform: all
Classifier: Programming Language :: Python
Classifier: Operating System :: Microsoft :: Windows
Classifier: Operating System :: Unix
Classifier: Programming Language :: Python :: 2.7
Classifier: Programming Language :: Python :: 3.4
Classifier: Programming Language :: Python :: 3.5
Classifier: Programming Language :: Python :: 3.6
Requires-Dist: numpy
Requires-Dist: pandas
Requires-Dist: thriftpy2
Requires-Dist: pymysql
